pettobids/Pipfile
pettobids/README.md
pettobids/__init__.py
pettobids/cli.py
pettobids/ecat.py
pettobids/ecat2nii.py
pettobids/ecat_headers.json
pettobids/helper_functions.py
pettobids/read_ecat.py
pettobids/sidecar.py
pettobids/template.env
pettobids-0.0.2.dist-info/entry_points.txt
pettobids-0.0.2.dist-info/WHEEL
pettobids-0.0.2.dist-info/METADATA
pettobids-0.0.2.dist-info/RECORD
